{
  "active_train": "TRAIN-PR173-PR175-AUDIT-WORKER",
  "status": "in_progress",
  "last_completed_train": "TRAIN-PR169-PR172-SCOUT-STAGING",
  "next_recommended_train": "TRAIN-PR173-PR175-AUDIT-WORKER",
  "notes": "PR174 / AUDIT_WORKER1 completed the fixture-only local small-batch audit dry-run with result PASS_AUDIT_WORKER_FIXTURE_DRY_RUN. Continue with PR175 / AUDIT_WORKERQ after PR174 is merged and local main is clean. No data repo, public surface, Supabase/staging/production, real audit run, browser fallback, deploy, Public API/MCP, sitemap, worker, crawler, queue, script/package/runtime/schema change, report surface, or server/cloud mutation occurred."
}
