{
  "current_task": "PR182A",
  "current_alias": "PROJECT_CONTRACT_MIGRATION_CHECKPOINT",
  "current_repo": "88CN",
  "current_role": "codex-ops",
  "status": "validation_passed",
  "result": "READY_FOR_PR182B_WITH_HUMAN_CHECKPOINT",
  "next_recommended_task": "PR182B",
  "next_recommended_alias": "PROJECT_CONTRACT_STAGING_SCHEMA_APPLY",
  "next_recommended_train": "TRAIN-PR183-CONTROL-PANEL",
  "next_non_pr_task": "PROJECT_CONTRACT_STAGING_SCHEMA_APPLY",
  "notes": "PR182A scans current Supabase/migration posture and converts PR182 into a staging schema migration readiness plan with result READY_FOR_PR182B_WITH_HUMAN_CHECKPOINT. Existing migrations 001-012, RLS conventions, public.projects, and admin-only review/import tables are present, but no PR182 staging namespace or project contract table family exists. The report defines future table matrices, lifecycle enum storage, fail-closed RLS/visibility principles, markdown-only SQL draft, seed import boundary, rollback/retention policy, Aliyun/Tencent relevance statement, and PR182B checkpoint requirements. No supabase migration file, Supabase connection, DB/staging/production write, seed import, frontend/admin UI implementation, sitemap/API/MCP exposure, data repo mutation, server/cloud action, or private seed artifact commit occurred. Exact next task is PR182B / PROJECT_CONTRACT_STAGING_SCHEMA_APPLY; PR182B is registered but not started. Train registry remains on TRAIN-PR183-CONTROL-PANEL because current batch validators do not accept suffixed PR IDs such as PR182B."
}
